<Context docBase="D:\WORK\SVG30\SVG30WEB" path="/svg" reloadable="false">
	<Resource name="jdbc/jfw3" auth="Container" type="javax.sql.DataSource"/>
	<ResourceParams name="jdbc/jfw3">
		<parameter>
			<name>factory</name>
			<value>org.apache.commons.dbcp.BasicDataSourceFactory</value>
		</parameter>
		<parameter>
			<name>maxActive</name>
			<value>20</value>
		</parameter>
		<parameter>
			<name>maxIdle</name>
			<value>10</value>
		</parameter>
		<parameter>
			<name>maxWait</name>
			<value>100000</value>
		</parameter>

		<parameter>
			<name>username</name>
			<value>svg</value>
		</parameter>
		<parameter>
			<name>password</name>
			<value>svg</value>
		</parameter>

		<parameter>
			<name>driverClassName</name>
			<value>oracle.jdbc.driver.OracleDriver</value>
		</parameter>
		
		<parameter>
			<name>url</name>
			<value>jdbc:oracle:thin:@localhost:1521:zhm</value>
			<!--value>jdbc:oracle:thin:@192.168.0.57:1521:ncird</value-->
		</parameter>
	</ResourceParams>
</Context>